dbt/__init__.py
dbt/adapters/__init__.py
dbt/adapters/sqlserver/__init__.py
dbt/adapters/sqlserver/__version__.py
dbt/adapters/sqlserver/sql_server_adapter.py
dbt/adapters/sqlserver/sql_server_column.py
dbt/adapters/sqlserver/sql_server_configs.py
dbt/adapters/sqlserver/sql_server_connection_manager.py
dbt/adapters/sqlserver/sql_server_credentials.py
dbt/include/__init__.py
dbt/include/sqlserver/__init__.py
dbt/include/sqlserver/dbt_project.yml
dbt/include/sqlserver/macros/adapters/apply_grants.sql
dbt/include/sqlserver/macros/adapters/columns.sql
dbt/include/sqlserver/macros/adapters/freshness.sql
dbt/include/sqlserver/macros/adapters/indexes.sql
dbt/include/sqlserver/macros/adapters/metadata.sql
dbt/include/sqlserver/macros/adapters/persist_docs.sql
dbt/include/sqlserver/macros/adapters/relation.sql
dbt/include/sqlserver/macros/adapters/schema.sql
dbt/include/sqlserver/macros/materializations/models/incremental/incremental_strategies.sql
dbt/include/sqlserver/macros/materializations/models/incremental/merge.sql
dbt/include/sqlserver/macros/materializations/models/table/create_table_as.sql
dbt/include/sqlserver/macros/materializations/models/view/create_view_as.sql
dbt/include/sqlserver/macros/materializations/seeds/helpers.sql
dbt/include/sqlserver/macros/materializations/snapshots/snapshot.sql
dbt/include/sqlserver/macros/materializations/snapshots/snapshot_merge.sql
dbt/include/sqlserver/macros/materializations/snapshots/strategies.sql
dbt/include/sqlserver/macros/materializations/tests/helpers.sql
dbt/include/sqlserver/macros/materializations/tests/test.sql
dbt/include/sqlserver/macros/utils/any_value.sql
dbt/include/sqlserver/macros/utils/array_construct.sql
dbt/include/sqlserver/macros/utils/cast_bool_to_text.sql
dbt/include/sqlserver/macros/utils/concat.sql
dbt/include/sqlserver/macros/utils/date_trunc.sql
dbt/include/sqlserver/macros/utils/dateadd.sql
dbt/include/sqlserver/macros/utils/hash.sql
dbt/include/sqlserver/macros/utils/last_day.sql
dyvenia_dbt_sqlserver-1.3.2.dist-info/LICENSE
dyvenia_dbt_sqlserver-1.3.2.dist-info/METADATA
dyvenia_dbt_sqlserver-1.3.2.dist-info/WHEEL
dyvenia_dbt_sqlserver-1.3.2.dist-info/top_level.txt
dyvenia_dbt_sqlserver-1.3.2.dist-info/RECORD
