Metadata-Version: 2.1
Name: dyvenia-dbt-sqlserver
Version: 1.3.2
Summary: A Microsoft SQL Server adapter plugin for dbt tailored to the dyvenia needs
Home-page: https://github.com/dbt-msft/dbt-sqlserver
Author: Mikael Ene, Anders Swanson, Sam Debruyn, Cor Zuurmond
License: MIT
Classifier: Development Status :: 5 - Production/Stable
Classifier: License :: OSI Approved :: MIT License
Classifier: Operating System :: Microsoft :: Windows
Classifier: Operating System :: MacOS :: MacOS X
Classifier: Operating System :: POSIX :: Linux
Classifier: Programming Language :: Python :: 3.7
Classifier: Programming Language :: Python :: 3.8
Classifier: Programming Language :: Python :: 3.9
Classifier: Programming Language :: Python :: 3.10
License-File: LICENSE
Requires-Dist: dbt-core (~=1.3.4)
Requires-Dist: pyodbc (!=4.0.34,>=4.0.32)
Requires-Dist: azure-identity (>=1.10.0)
